mapr_streams_python/__init__.py
mapr_streams_python/cimpl.cpython-35m-x86_64-linux-gnu.so
mapr_streams_python/kafkatest/__init__.py
mapr_streams_python/kafkatest/verifiable_client.py
mapr_streams_python/kafkatest/verifiable_consumer.py
mapr_streams_python/kafkatest/verifiable_producer.py
mapr_streams_python_slayv-0.11.0-7.data/data/LICENSE
mapr_streams_python_slayv-0.11.0.dist-info/LICENSE
mapr_streams_python_slayv-0.11.0.dist-info/METADATA
mapr_streams_python_slayv-0.11.0.dist-info/WHEEL
mapr_streams_python_slayv-0.11.0.dist-info/top_level.txt
mapr_streams_python_slayv-0.11.0.dist-info/RECORD
