Metadata-Version: 2.1
Name: mapr-streams-python-slayv
Version: 0.11.0
Summary: MapR Streams Python Client
Home-page: https://github.com/mapr/private-kafka-python
Author: Confluent Inc & MapR
Author-email: support@mapr.com
License: UNKNOWN
Platform: UNKNOWN
